aiy_worker/__init__.py
aiy_worker/types.py
aiy_worker/utils.py
aiy_worker/worker.py
aiy_worker/ws_client.py
aiy_worker-0.0.17.dist-info/METADATA
aiy_worker-0.0.17.dist-info/WHEEL
aiy_worker-0.0.17.dist-info/top_level.txt
aiy_worker-0.0.17.dist-info/RECORD
