Metadata-Version: 2.1
Name: aiy-worker
Version: 0.0.17
Summary: aiy worker
Author: zgljl2012
Classifier: Programming Language :: Python :: 3
Classifier: License :: OSI Approved :: MIT License
Classifier: Operating System :: OS Independent
Requires-Dist: websocket-client ==1.7.0
Requires-Dist: requests ==2.31.0
Requires-Dist: pngquant ==1.0.7
Requires-Dist: pillow ==10.2.0
Requires-Dist: zopflipng ==1.1.1
Requires-Dist: pillow-avif-plugin ==1.4.3
